psychrnn/__init__.py
psychrnn/_version.py
psychrnn/backend/__init__.py
psychrnn/backend/curriculum.py
psychrnn/backend/initializations.py
psychrnn/backend/loss_functions.py
psychrnn/backend/regularizations.py
psychrnn/backend/rnn.py
psychrnn/backend/simulation.py
psychrnn/backend/models/__init__.py
psychrnn/backend/models/basic.py
psychrnn/backend/models/lstm.py
psychrnn/tasks/__init__.py
psychrnn/tasks/delayed_discrim.py
psychrnn/tasks/match_to_category.py
psychrnn/tasks/perceptual_discrimination.py
psychrnn/tasks/task.py
PsychRNN-1.0.0.dist-info/LICENSE
PsychRNN-1.0.0.dist-info/METADATA
PsychRNN-1.0.0.dist-info/WHEEL
PsychRNN-1.0.0.dist-info/top_level.txt
PsychRNN-1.0.0.dist-info/RECORD
