Metadata-Version: 2.1
Name: PsychRNN
Version: 1.0.0
Summary: Easy-to-use package for the modeling and analysis of neural network dynamics, directed towards cognitive neuroscientists.
Home-page: https://github.com/murraylab/PsychRNN
Author: Daniel Ehrlich, Jasmine Stone, Alex Atanasov, David Brandfonbrener
Author-email: psychrnn@gmail.com
License: MIT
Project-URL: Documentation, https://psychrnn.readthedocs.io/
Project-URL: Mailing List, https://www.freelists.org/list/psychrnn
Keywords: neuroscience,modeling,analysis,neural networks
Platform: UNKNOWN
Requires-Dist: python-version (!="3.0*",!="3.1*",!="3.2*",!="3.3*",>="2.7")
Requires-Dist: tensorflow
